binubuo/BinubuoTemplate.py
binubuo/__init__.py
binubuo/binubuo.py
binubuo/binubuoCSV.py
binubuo/binubuoExcel.py
binubuo/binubuoOracle.py
binubuo/binubuoPostgres.py
binubuo/binubuoSQLServer.py
binubuo/binubuoYugabyte.py
binubuo/SQL/all.sql
binubuo/SQL/oracle_assert_table.sql
binubuo/SQL/oracle_build_insert.sql
binubuo/SQL/oracle_column_meta_plus_sample.sql
binubuo/SQL/oracle_column_meta_plus_standard.sql
binubuo/SQL/oracle_column_meta_simple.sql
binubuo/SQL/oracle_column_sample_data.sql
binubuo/SQL/oracle_columns_ordered.sql
binubuo/SQL/oracle_comments_ordered.sql
binubuo/SQL/oracle_count_comments.sql
binubuo/SQL/oracle_current_user.sql
binubuo/SQL/oracle_foreign_key_depends.sql
binubuo/SQL/oracle_foreign_key_histogram.sql
binubuo/SQL/oracle_nls_date_format.sql
binubuo/SQL/oracle_nls_timestamp_format.sql
binubuo/SQL/oracle_nls_timestamp_tz_format.sql
binubuo/SQL/oracle_prepare_dbms_metadata.sql
binubuo/SQL/oracle_sample_select.sql
binubuo/SQL/oracle_table_ddl.sql
binubuo/SQL/oracle_table_hierachy_schema.sql
binubuo/SQL/oracle_table_rows.sql
binubuo/SQL/postgres_assert_table.sql
binubuo/SQL/postgres_build_insert.sql
binubuo/SQL/postgres_column_meta_plus_sample.sql
binubuo/SQL/postgres_column_meta_plus_standard.sql
binubuo/SQL/postgres_column_meta_simple.sql
binubuo/SQL/postgres_column_sample_data.sql
binubuo/SQL/postgres_columns_ordered.sql
binubuo/SQL/postgres_comments_ordered.sql
binubuo/SQL/postgres_count_comments.sql
binubuo/SQL/postgres_foreign_key_depends.sql
binubuo/SQL/postgres_foreign_key_histogram.sql
binubuo/SQL/postgres_sample_select.sql
binubuo/SQL/postgres_table_analyzed.sql
binubuo/SQL/postgres_table_ddl.sql
binubuo/SQL/postgres_table_hierachy_schema.sql
binubuo/SQL/postgres_table_rows.sql
binubuo/SQL/postgres_table_rows_not_analysed.sql
binubuo/SQL/sqlserver_assert_table.sql
binubuo/SQL/sqlserver_build_insert.sql
binubuo/SQL/sqlserver_column_meta_plus_sample.sql
binubuo/SQL/sqlserver_column_meta_plus_standard.sql
binubuo-0.2.1.dist-info/LICENSE.txt
binubuo-0.2.1.dist-info/METADATA
binubuo-0.2.1.dist-info/WHEEL
binubuo-0.2.1.dist-info/top_level.txt
binubuo-0.2.1.dist-info/RECORD
