Metadata-Version: 2.1
Name: binubuo
Version: 0.2.1
Summary: Client package for Binubuo synthetic data generator
Home-page: https://binubuo.com
Author: Morten
Author-email: morten@binubuo.com
Project-URL: Documentation, https://binubuo.com/ords/r/binubuo_ui/binubuo/binubuo-documentation
Project-URL: Bug Reports, https://github.com/morten-egan/binubuo-python-client/issues/new
Keywords: synthetic,testdata,mocking
Classifier: Development Status :: 3 - Alpha
Classifier: Intended Audience :: Developers
Classifier: Intended Audience :: Science/Research
Classifier: Intended Audience :: System Administrators
Classifier: Environment :: Console
Classifier: Operating System :: OS Independent
Classifier: Programming Language :: Python
Classifier: Topic :: Database
Classifier: Topic :: Software Development
Classifier: Topic :: Software Development :: Testing :: Mocking
Classifier: Topic :: Utilities
Requires-Python: >=2.7, !=3.0.*, !=3.1.*, !=3.2.*
License-File: LICENSE.txt
Requires-Dist: requests>=2.0.0; python_version >= "3"
